dlclivegui/__init__.py
dlclivegui/camera_process.py
dlclivegui/dlclivegui.py
dlclivegui/pose_process.py
dlclivegui/queue.py
dlclivegui/tkutil.py
dlclivegui/video.py
dlclivegui/camera/__init__.py
dlclivegui/camera/aravis.py
dlclivegui/camera/camera.py
dlclivegui/camera/opencv.py
dlclivegui/camera/pseye.py
dlclivegui/camera/tiscamera_linux.py
dlclivegui/camera/tiscamera_windows.py
dlclivegui/camera/tisgrabber_windows.py
dlclivegui/processor/__init__.py
dlclivegui/processor/processor.py
dlclivegui/processor/teensy_laser/__init__.py
dlclivegui/processor/teensy_laser/teensy_laser.py
deeplabcut_live_gui-1.0.dist-info/LICENSE
deeplabcut_live_gui-1.0.dist-info/METADATA
deeplabcut_live_gui-1.0.dist-info/WHEEL
deeplabcut_live_gui-1.0.dist-info/entry_points.txt
deeplabcut_live_gui-1.0.dist-info/top_level.txt
deeplabcut_live_gui-1.0.dist-info/RECORD
