Metadata-Version: 2.1
Name: deeplabcut-live-gui
Version: 1.0
Summary: GUI to run real time deeplabcut experiments
Home-page: https://github.com/DeepLabCut/DeepLabCut-live-GUI
Author: A. & M. Mathis Labs
Author-email: adim@deeplabcut.org
License: UNKNOWN
Platform: UNKNOWN
Classifier: Programming Language :: Python :: 3
Classifier: License :: OSI Approved :: GNU Lesser General Public License v3 (LGPLv3)
Classifier: Operating System :: OS Independent
Requires-Python: >=3.5, <3.8
Requires-Dist: deeplabcut-live
Requires-Dist: pyserial
Requires-Dist: pandas
Requires-Dist: tables
Requires-Dist: multiprocess
Requires-Dist: imutils
Requires-Dist: pillow
Requires-Dist: tqdm
